LICENSE
MANIFEST.in
README.rst
setup.cfg
setup.py
txes2/__init__.py
txes2/connection.py
txes2/connection_http.py
txes2/elasticsearch.py
txes2/exceptions.py
txes2/utils.py
txes2.egg-info/PKG-INFO
txes2.egg-info/SOURCES.txt
txes2.egg-info/dependency_links.txt
txes2.egg-info/not-zip-safe
txes2.egg-info/requires.txt
txes2.egg-info/top_level.txt