Metadata-Version: 1.1
Name: txes2
Version: 2.1.0
Summary: An Elasticsearch client for Twisted
Home-page: https://github.com/lextoumbourou/txes2
Author: Lex Toumbourou
Author-email: lextoumbourou@gmail.com
License: BSD License
Keywords: twisted elasticsearch
Platform: UNKNOWN
Classifier: License :: OSI Approved :: BSD License
Classifier: Programming Language :: Python
